qos_tools/analyzer/__init__.py
qos_tools/analyzer/cr.py
qos_tools/analyzer/gpr.py
qos_tools/analyzer/lib.py
qos_tools/analyzer/statistics.py
qos_tools/analyzer/tools.py
qos_tools/bigBrother/__init__.py
qos_tools/core/__init__.py
qos_tools/core/_async_utils.py
qos_tools/core/_cfgcontext.py
qos_tools/core/_cm.py
qos_tools/core/_d2c.py
qos_tools/core/_dag_cons_manager.py
qos_tools/core/_dict_utils.py
qos_tools/core/_equal_utils.py
qos_tools/core/_graph_func.py
qos_tools/core/_iter.py
qos_tools/create/__init__.py
qos_tools/create/create.py
qos_tools/create/map.py
qos_tools/experiment/__init__.py
qos_tools/experiment/lib.py
qos_tools/experiment/quark.py
qos_tools/experiment/scanner.py
qos_tools/experiment/scanner2.py
qos_tools/experiment/transform.py
qos_tools/experiment/libs/CR.py
qos_tools/experiment/libs/__init__.py
qos_tools/experiment/libs/coherence.py
qos_tools/experiment/libs/fidelity.py
qos_tools/experiment/libs/readout.py
qos_tools/experiment/libs/rfUnitary.py
qos_tools/experiment/libs/rfUnitary12.py
qos_tools/experiment/libs/tools.py
qos_tools/feedback/BayesOpt.py
qos_tools/feedback/__init__.py
qos_tools/feedback/model.py
qos_tools/feedback/ngOpt.py
qos_tools/fit/__init__.py
qos_tools/fit/fitclass.py
qos_tools/fit/fitfunc.py
qos_tools/fit/fitindex.py
qos_tools/fit/function.py
qos_tools/fit/plotscript.py
qos_tools/gatemap/__info_extract.py
qos_tools/gatemap/__init__.py
qos_tools/gatemap/_circuit_convert.py
qos_tools/gatemap/_cmd_convert.py
qos_tools/gatemap/_index_convert.py
qos_tools-0.0.1.dist-info/LICENSE
qos_tools-0.0.1.dist-info/METADATA
qos_tools-0.0.1.dist-info/WHEEL
qos_tools-0.0.1.dist-info/top_level.txt
qos_tools-0.0.1.dist-info/RECORD
