Metadata-Version: 2.1
Name: qos-tools
Version: 0.0.1
License-File: LICENSE
Requires-Dist: waveforms
